dask_iclx/__init__.py
dask_iclx/cluster.py
dask_iclx/config.py
dask_iclx/jobqueue-ic.yaml
dask_iclx-0.5.2.dist-info/licenses/LICENSE.txt
dask_iclx-0.5.2.dist-info/METADATA
dask_iclx-0.5.2.dist-info/WHEEL
dask_iclx-0.5.2.dist-info/top_level.txt
dask_iclx-0.5.2.dist-info/RECORD
