Metadata-Version: 2.4
Name: dask_iclx
Version: 0.5.2
Home-page: https://github.com/runtingt/dask-iclx
Author: Tom Runting, Ben Jones
Author-email: thomas.runting@cern.ch, b.jones@cern.ch
Classifier: Development Status :: 3 - Alpha
Classifier: Intended Audience :: Developers
Classifier: Intended Audience :: Science/Research
Classifier: Operating System :: OS Independent
Classifier: Programming Language :: Python :: 3
Classifier: Programming Language :: Python :: 3 :: Only
Classifier: Programming Language :: Python :: 3.8
Classifier: Programming Language :: Python :: 3.9
Classifier: Programming Language :: Python :: 3.10
Classifier: Programming Language :: Python :: 3.11
Classifier: Programming Language :: Python :: 3.12
Classifier: Programming Language :: Python :: 3.13
Classifier: Topic :: System :: Distributed Computing
Requires-Python: >=3.8
License-File: LICENSE.txt
Requires-Dist: click>=7.0
Requires-Dist: click-didyoumean
Requires-Dist: cryptography
Requires-Dist: dask
Requires-Dist: dask-jobqueue>=0.8.1
Requires-Dist: humanize
Requires-Dist: psutil
Requires-Dist: pyyaml
Requires-Dist: watchdog
Requires-Dist: importlib-metadata>=1.0
Provides-Extra: dev
Requires-Dist: pytest>=6.0; extra == "dev"
Requires-Dist: pytest-cov>=3.0; extra == "dev"
Requires-Dist: coverage[toml]>=6.0; extra == "dev"
Requires-Dist: pytest-html; extra == "dev"
Requires-Dist: pytest-xdist; extra == "dev"
Requires-Dist: pyfakefs; extra == "dev"
Requires-Dist: pytest-md-report; extra == "dev"
Dynamic: license-file
